AutoMessenger/__init__.py
AutoMessenger/auto_messenger.py
AutoMessenger-0.2.dist-info/LICENSE
AutoMessenger-0.2.dist-info/METADATA
AutoMessenger-0.2.dist-info/WHEEL
AutoMessenger-0.2.dist-info/top_level.txt
AutoMessenger-0.2.dist-info/RECORD
