Metadata-Version: 2.1
Name: AutoMessenger
Version: 0.2
Summary: A Python package to send automated messages using pyautogui
Home-page: https://github.com/imzulkar/automessnger
Author: GM Zulkar Nine
Author-email: gmzulkar@gmail.com
License: MIT
Classifier: Programming Language :: Python :: 3
Classifier: License :: OSI Approved :: MIT License
Classifier: Operating System :: OS Independent
Requires-Python: >=3.6
License-File: LICENSE
Requires-Dist: pyautogui
